llama_index/llms/ibm/__init__.py
llama_index/llms/ibm/base.py
llama_index/llms/ibm/utils.py
llama_index_llms_ibm-0.6.0.dist-info/METADATA
llama_index_llms_ibm-0.6.0.dist-info/WHEEL
llama_index_llms_ibm-0.6.0.dist-info/licenses/LICENSE
llama_index_llms_ibm-0.6.0.dist-info/RECORD
