Metadata-Version: 2.4
Name: llama-index-llms-ibm
Version: 0.6.0
Summary: llama-index llms IBM watsonx.ai integration
Author: IBM
License-Expression: MIT
License-File: LICENSE
Requires-Python: <3.13,>=3.10
Requires-Dist: ibm-watsonx-ai>=1.3.36
Requires-Dist: llama-index-core<0.14,>=0.13.0
Requires-Dist: pyarrow
